zipremove/__init__.py
zipremove-0.7.1.dist-info/licenses/LICENSE.txt
zipremove-0.7.1.dist-info/METADATA
zipremove-0.7.1.dist-info/WHEEL
zipremove-0.7.1.dist-info/top_level.txt
zipremove-0.7.1.dist-info/RECORD
