Metadata-Version: 2.4
Name: zipremove
Version: 0.7.1
Summary: Extend `zipfile` with `remove`-related functionalities
Home-page: https://github.com/danny0838/zipremove
Author: Danny Lin
Author-email: danny0838@gmail.com
License: MIT
Classifier: Development Status :: 4 - Beta
Classifier: Intended Audience :: Developers
Classifier: Topic :: System :: Archiving :: Compression
Classifier: Programming Language :: Python :: 3
Classifier: Programming Language :: Python :: 3 :: Only
Classifier: Programming Language :: Python :: 3.9
Classifier: Programming Language :: Python :: 3.10
Classifier: Programming Language :: Python :: 3.11
Classifier: Programming Language :: Python :: 3.12
Classifier: Programming Language :: Python :: 3.13
Classifier: Programming Language :: Python :: 3.14
Classifier: Operating System :: OS Independent
Requires-Python: ~=3.9
License-File: LICENSE.txt
Dynamic: license-file
